README.rst
setup.cfg
setup.py
djangorestframework_timed_auth_token.egg-info/PKG-INFO
djangorestframework_timed_auth_token.egg-info/SOURCES.txt
djangorestframework_timed_auth_token.egg-info/dependency_links.txt
djangorestframework_timed_auth_token.egg-info/requires.txt
djangorestframework_timed_auth_token.egg-info/top_level.txt
timed_auth_token/__init__.py
timed_auth_token/admin.py
timed_auth_token/authentication.py
timed_auth_token/models.py
timed_auth_token/serializers.py
timed_auth_token/settings.py
timed_auth_token/urls.py
timed_auth_token/views.py