Metadata-Version: 1.1
Name: djangorestframework-timed-auth-token
Version: 1.0.1
Summary: An authentication token for djangorestframework that has an expiration date.
Home-page: https://github.com/silverlogic/djangorestframework-timed-auth-token
Author: Ryan Pineo
Author-email: ryanpineo@gmail.com
License: MIT
Platform: UNKNOWN
Classifier: Framework :: Django
Classifier: Programming Language :: Python :: 3
